gtnet/__init__.py
gtnet/classify.py
gtnet/filter.py
gtnet/main.py
gtnet/predict.py
gtnet/sequence.py
gtnet/utils.py
gtnet/data/GCA_000006155.2.fna
gtnet/deploy_pkg/last.pt
gtnet/deploy_pkg/manifest.json
gtnet/deploy_pkg/bins/class.roc.npz
gtnet/deploy_pkg/bins/class.score.pt
gtnet/deploy_pkg/bins/domain.roc.npz
gtnet/deploy_pkg/bins/domain.score.pt
gtnet/deploy_pkg/bins/family.roc.npz
gtnet/deploy_pkg/bins/family.score.pt
gtnet/deploy_pkg/bins/genus.roc.npz
gtnet/deploy_pkg/bins/genus.score.pt
gtnet/deploy_pkg/bins/order.roc.npz
gtnet/deploy_pkg/bins/order.score.pt
gtnet/deploy_pkg/bins/phylum.roc.npz
gtnet/deploy_pkg/bins/phylum.score.pt
gtnet/deploy_pkg/bins/species.roc.npz
gtnet/deploy_pkg/bins/species.score.pt
gtnet/deploy_pkg/contigs/class.roc.npz
gtnet/deploy_pkg/contigs/class.score.pt
gtnet/deploy_pkg/contigs/domain.roc.npz
gtnet/deploy_pkg/contigs/domain.score.pt
gtnet/deploy_pkg/contigs/family.roc.npz
gtnet/deploy_pkg/contigs/family.score.pt
gtnet/deploy_pkg/contigs/genus.roc.npz
gtnet/deploy_pkg/contigs/genus.score.pt
gtnet/deploy_pkg/contigs/order.roc.npz
gtnet/deploy_pkg/contigs/order.score.pt
gtnet/deploy_pkg/contigs/phylum.roc.npz
gtnet/deploy_pkg/contigs/phylum.score.pt
gtnet/deploy_pkg/contigs/species.roc.npz
gtnet/deploy_pkg/contigs/species.score.pt
gtnet-0.1.0.dist-info/METADATA
gtnet-0.1.0.dist-info/WHEEL
gtnet-0.1.0.dist-info/entry_points.txt
gtnet-0.1.0.dist-info/top_level.txt
gtnet-0.1.0.dist-info/RECORD
